llama_index/embeddings/vertex_endpoint/__init__.py
llama_index/embeddings/vertex_endpoint/base.py
llama_index/embeddings/vertex_endpoint/utils.py
llama_index_embeddings_vertex_endpoint-0.3.1.dist-info/METADATA
llama_index_embeddings_vertex_endpoint-0.3.1.dist-info/WHEEL
llama_index_embeddings_vertex_endpoint-0.3.1.dist-info/licenses/LICENSE
llama_index_embeddings_vertex_endpoint-0.3.1.dist-info/RECORD
