Metadata-Version: 2.4
Name: llama-index-embeddings-vertex-endpoint
Version: 0.3.1
Summary: llama-index embeddings vertex_endpoint integration
Author-email: Mohannad <mouhanned.lassioued@gmail.com>
License-Expression: MIT
License-File: LICENSE
Requires-Python: <4.0,>=3.9
Requires-Dist: google-cloud-aiplatform<2,>=1.69.0
Requires-Dist: llama-index-core<0.15,>=0.13.0
